ft_utils-0.1.0.dist-info/METADATA
ft_utils-0.1.0.dist-info/RECORD
ft_utils-0.1.0.dist-info/top_level.txt
ft_utils-0.1.0.dist-info/WHEEL
ft_utils-0.1.0.dist-info/LICENSE
ft_utils/_concurrency.cpython-313-x86_64-linux-musl.so
ft_utils/_weave.cpython-313-x86_64-linux-musl.so
ft_utils/weave.py
ft_utils/_test_weave.cpython-313-x86_64-linux-musl.so
ft_utils/local.cpython-313-x86_64-linux-musl.so
ft_utils/__init__.py
ft_utils/synchronization.cpython-313-x86_64-linux-musl.so
ft_utils/lock_test_utils.py
ft_utils/_test_compat.cpython-313-x86_64-linux-musl.so
ft_utils/benchmark_utils.py
ft_utils/concurrency.py
ft_utils/tests/merge_sort_bench.py
ft_utils/tests/test_compat.py
ft_utils/tests/lock_bench.py
ft_utils/tests/concurrent_queue_bench.py
ft_utils/tests/map_reduce_bench.py
ft_utils/tests/test_run_all.py
ft_utils/tests/test_rwlock.py
ft_utils/tests/concurrent_dict_bench.py
ft_utils/tests/concurrent_deque_bench.py
ft_utils/tests/test_concurrency.py
ft_utils/tests/slots_bench.py
ft_utils/tests/test_batchexecutor.py
ft_utils/tests/tsp_bench.py
ft_utils/tests/__init__.py
ft_utils/tests/test_weakref_to.py
ft_utils/tests/test_intervallock.py
ft_utils/tests/test_weave.py
ft_utils/tests/test_localwrapper.py
ft_utils/tests/list_bench.py
ft_utils/tests/random_bench.py
ft_utils/tests/atomic_bench.py
ft_utils/tests/test_benchmark_utils.py
