Metadata-Version: 2.2
Name: ft_utils
Version: 0.1.0
Summary: A utility library for Free Threaded Python programming
Home-page: https://github.com/facebookincubator/ft_utils
Author: Meta Platforms, Inc.
Author-email: open-source@fb.com
License: MIT
Classifier: Development Status :: 4 - Beta
Classifier: Intended Audience :: Developers
Classifier: License :: OSI Approved :: MIT License
Classifier: Programming Language :: Python :: 3.12
Classifier: Programming Language :: Python :: 3.13
Classifier: Programming Language :: Python :: 3.14
License-File: LICENSE
Dynamic: author
Dynamic: author-email
Dynamic: classifier
Dynamic: description
Dynamic: description-content-type
Dynamic: home-page
Dynamic: license
Dynamic: summary
